Metadata-Version: 2.1
Name: espeak-phonemizer
Version: 1.2.0
Summary: Lightweight International Phonetic Alphabet (IPA) phonemizer that uses libespeak-ng
Home-page: https://github.com/rhasspy/espeak-phonemizer
Author: Michael Hansen
Author-email: mike@rhasspy.org
License: UNKNOWN
Platform: UNKNOWN
Classifier: Programming Language :: Python :: 3
Classifier: Programming Language :: Python :: 3.7
Classifier: Programming Language :: Python :: 3.8
Classifier: License :: OSI Approved :: MIT License
License-File: LICENSE
